<Properties StartupConfiguration="{ADE3E85B-1FCD-4099-9F0B-C02AE3260562}|Default">
  <MonoDevelop.Ide.Workbench ActiveDocument="obj/Debug/net6.0/Catalog.GlobalUsings.g.cs">
    <Files>
      <File FileName="obj/Debug/net6.0/Catalog.GlobalUsings.g.cs" Line="13" Column="1" />
    </Files>
    <Pads>
      <Pad Id="ProjectPad">
        <State name="__root__">
          <Node name="Catalog" expanded="True">
            <Node name="Catalog" expanded="True">
              <Node name="Dependencies" expanded="True">
                <Node name="PackageDependencies" selected="True" />
              </Node>
            </Node>
          </Node>
        </State>
      </Pad>
    </Pads>
  </MonoDevelop.Ide.Workbench>
  <MonoDevelop.Ide.ItemProperties.Catalog PreferredExecutionTarget="/Applications/Firefox.app" />
  <MonoDevelop.Ide.DebuggingService.PinnedWatches />
  <MonoDevelop.Ide.Workspace ActiveConfiguration="Debug" />
  <MonoDevelop.Ide.DebuggingService.Breakpoints>
    <BreakpointStore />
  </MonoDevelop.Ide.DebuggingService.Breakpoints>
  <MultiItemStartupConfigurations />
</Properties>